functions/__init__.py
functions/cross_correlation.py
functions/time_series_windowing.py
functions/transpose.py
jmarci_de2v2_1_5-0.1.1.dist-info/METADATA
jmarci_de2v2_1_5-0.1.1.dist-info/WHEEL
jmarci_de2v2_1_5-0.1.1.dist-info/RECORD
