Metadata-Version: 2.1
Name: jmarci-de2v2-1-5
Version: 0.1.1
Summary: Data Transformation Library
Author: Julius
Author-email: j.marciulynas@gmail.com
Requires-Python: >=3.12,<4.0
Classifier: Programming Language :: Python :: 3
Classifier: Programming Language :: Python :: 3.12
Requires-Dist: numpy (>=2.0.1,<3.0.0)
